MANIFEST.in
README.txt
setup.py
docs/HISTORY.txt
silva/__init__.py
silva.searchandreplace.egg-info/PKG-INFO
silva.searchandreplace.egg-info/SOURCES.txt
silva.searchandreplace.egg-info/dependency_links.txt
silva.searchandreplace.egg-info/namespace_packages.txt
silva.searchandreplace.egg-info/not-zip-safe
silva.searchandreplace.egg-info/requires.txt
silva.searchandreplace.egg-info/top_level.txt
silva/searchandreplace/SearchReplaceService.py
silva/searchandreplace/__init__.py
silva/searchandreplace/configure.zcml
silva/searchandreplace/searchreplaceservice.png
silva/searchandreplace/tests/__init__.py
silva/searchandreplace/tests/test_SearchReplaceService.py
silva/searchandreplace/www/serviceSearchReplaceAdd.zpt
silva/searchandreplace/www/serviceSearchReplaceEdit.zpt