Metadata-Version: 1.1
Name: silva.searchandreplace
Version: 2.1
Summary: Search in all Silva Documents and replace information
Home-page: UNKNOWN
Author: Guido Wesdorp
Author-email: info@infrae.com
License: BSD
Keywords: silva silvadocument search replace service
Platform: UNKNOWN
Classifier: Framework :: Zope2
Classifier: Programming Language :: Python
Classifier: Topic :: Software Development :: Libraries :: Python Modules
Classifier: License :: OSI Approved :: BSD License
